<response><header><resultCode>00</resultCode><resultMsg>NORMAL SERVICE.</resultMsg></header><body><numOfRows>100</numOfRows><pageNo>172</pageNo><totalCount>22629</totalCount><items><item><DESC_KOR>카페라떼커피카푸치노</DESC_KOR><SERVING_WT>200</SERVING_WT><NUTR_CONT1>249.76</NUTR_CONT1><NUTR_CONT2>34.6</NUTR_CONT2><NUTR_CONT3>7.68</NUTR_CONT3><NUTR_CONT4>8.64</NUTR_CONT4><NUTR_CONT5>22.52</NUTR_CONT5><NUTR_CONT6>182.52</NUTR_CONT6><NUTR_CONT7>19.2</NUTR_CONT7><NUTR_CONT8>5.76</NUTR_CONT8><NUTR_CONT9>0</NUTR_CONT9><BGN_YEAR>2017</BGN_YEAR><ANIMAL_PLANT>매일유업</ANIMAL_PLANT></item><item><DESC_KOR>카페라떼커피카라멜마끼아또</DESC_KOR><SERVING_WT>200</SERVING_WT><NUTR_CONT1>119.74</NUTR_CONT1><NUTR_CONT2>17.24</NUTR_CONT2><NUTR_CONT3>2.88</NUTR_CONT3><NUTR_CONT4>4.4</NUTR_CONT4><NUTR_CONT5>17.24</NUTR_CONT5><NUTR_CONT6>105.36</NUTR_CONT6><NUTR_CONT7>16.28</NUTR_CONT7><NUTR_CONT8>2.88</NUTR_CONT8><NUTR_CONT9>0</NUTR_CONT9><BGN_YEAR>2015</BGN_YEAR><ANIMAL_PLANT>매일유업</ANIMAL_PLANT></item><item><DESC_KOR>카페라떼커피카라멜마끼아또</DESC_KOR><SERVING_WT>200</SERVING_WT><NUTR_CONT1>239.48</NUTR_CONT1><NUTR_CONT2>34.48</NUTR_CONT2><NUTR_CONT3>5.76</NUTR_CONT3><NUTR_CONT4>8.8</NUTR_CONT4><NUTR_CONT5>76</NUTR_CONT5><NUTR_CONT6>210.72</NUTR_CONT6><NUTR_CONT7>32.56</NUTR_CONT7><NUTR_CONT8>5.76</NUTR_CONT8><NUTR_CONT9>0</NUTR_CONT9><BGN_YEAR>2017</BGN_YEAR><ANIMAL_PLANT>매일유업</ANIMAL_PLANT></item><item><DESC_KOR>카페라떼녹차라떼</DESC_KOR><SERVING_WT>200</SERVING_WT><NUTR_CONT1>149.52</NUTR_CONT1><NUTR_CONT2>20.96</NUTR_CONT2><NUTR_CONT3>5.72</NUTR_CONT3><NUTR_CONT4>4.76</NUTR_CONT4><NUTR_CONT5>19.04</NUTR_CONT5><NUTR_CONT6>128.58</NUTR_CONT6><NUTR_CONT7>10.48</NUTR_CONT7><NUTR_CONT8>2.86</NUTR_CONT8><NUTR_CONT9>0</NUTR_CONT9><BGN_YEAR>2015</BGN_YEAR><ANIMAL_PLANT>매일유업</ANIMAL_PLANT></item><item><DESC_KOR>카페라떼녹차라떼</DESC_KOR><SERVING_WT>200</SERVING_WT><NUTR_CONT1>299.04</NUTR_CONT1><NUTR_CONT2>41.92</NUTR_CONT2><NUTR_CONT3>11.44</NUTR_CONT3><NUTR_CONT4>9.52</NUTR_CONT4><NUTR_CONT5>32.68</NUTR_CONT5><NUTR_CONT6>257.16</NUTR_CONT6><NUTR_CONT7>20.96</NUTR_CONT7><NUTR_CONT8>5.72</NUTR_CONT8><NUTR_CONT9>0</NUTR_CONT9><BGN_YEAR>2017</BGN_YEAR><ANIMAL_PLANT>매일유업</ANIMAL_PLANT></item><item><DESC_KOR>카페라떼초콜릿라떼</DESC_KOR><SERVING_WT>200</SERVING_WT><NUTR_CONT1>182.16</NUTR_CONT1><NUTR_CONT2>26.3</NUTR_CONT2><NUTR_CONT3>6.58</NUTR_CONT3><NUTR_CONT4>5.64</NUTR_CONT4><NUTR_CONT5>18.78</NUTR_CONT5><NUTR_CONT6>183.1</NUTR_CONT6><NUTR_CONT7>11.26</NUTR_CONT7><NUTR_CONT8>3.76</NUTR_CONT8><NUTR_CONT9>0</NUTR_CONT9><BGN_YEAR>2015</BGN_YEAR><ANIMAL_PLANT>매일유업</ANIMAL_PLANT></item><item><DESC_KOR>카페라떼초콜릿라떼</DESC_KOR><SERVING_WT>200</SERVING_WT><NUTR_CONT1>364.32</NUTR_CONT1><NUTR_CONT2>52.6</NUTR_CONT2><NUTR_CONT3>13.16</NUTR_CONT3><NUTR_CONT4>11.28</NUTR_CONT4><NUTR_CONT5>30.71</NUTR_CONT5><NUTR_CONT6>366.2</NUTR_CONT6><NUTR_CONT7>22.52</NUTR_CONT7><NUTR_CONT8>7.52</NUTR_CONT8><NUTR_CONT9>0</NUTR_CONT9><BGN_YEAR>2017</BGN_YEAR><ANIMAL_PLANT>매일유업</ANIMAL_PLANT></item><item><DESC_KOR>바리스타모카프레소</DESC_KOR><SERVING_WT>200</SERVING_WT><NUTR_CONT1>114.94</NUTR_CONT1><NUTR_CONT2>16.1</NUTR_CONT2><NUTR_CONT3>3.06</NUTR_CONT3><NUTR_CONT4>4.22</NUTR_CONT4><NUTR_CONT5>16.1</NUTR_CONT5><NUTR_CONT6>114.94</NUTR_CONT6><NUTR_CONT7>15.32</NUTR_CONT7><NUTR_CONT8>2.68</NUTR_CONT8><NUTR_CONT9>0</NUTR_CONT9><BGN_YEAR>2015</BGN_YEAR><ANIMAL_PLANT>매일유업</ANIMAL_PLANT></item><item><DESC_KOR>바리스타모카프레소</DESC_KOR><SERVING_WT>200</SERVING_WT><NUTR_CONT1>229.88</NUTR_CONT1><NUTR_CONT2>32.2</NUTR_CONT2><NUTR_CONT3>6.12</NUTR_CONT3><NUTR_CONT4>8.44</NUTR_CONT4><NUTR_CONT5>205.25</NUTR_CONT5><NUTR_CONT6>229.88</NUTR_CONT6><NUTR_CONT7>30.64</NUTR_CONT7><NUTR_CONT8>5.36</NUTR_CONT8><NUTR_CONT9>0</NUTR_CONT9><BGN_YEAR>2017</BGN_YEAR><ANIMAL_PLANT>매일유업</ANIMAL_PLANT></item><item><DESC_KOR>바리스타에스프레소라떼</DESC_KOR><SERVING_WT>200</SERVING_WT><NUTR_CONT1>111.44</NUTR_CONT1><NUTR_CONT2>15.36</NUTR_CONT2><NUTR_CONT3>3.08</NUTR_CONT3><NUTR_CONT4>4.22</NUTR_CONT4><NUTR_CONT5>15.36</NUTR_CONT5><NUTR_CONT6>115.28</NUTR_CONT6><NUTR_CONT7>15.36</NUTR_CONT7><NUTR_CONT8>2.68</NUTR_CONT8><NUTR_CONT9>0</NUTR_CONT9><BGN_YEAR>2015</BGN_YEAR><ANIMAL_PLANT>매일유업</ANIMAL_PLANT></item><item><DESC_KOR>바리스타에스프레소라떼</DESC_KOR><SERVING_WT>200</SERVING_WT><NUTR_CONT1>222.88</NUTR_CONT1><NUTR_CONT2>30.72</NUTR_CONT2><NUTR_CONT3>6.16</NUTR_CONT3><NUTR_CONT4>8.44</NUTR_CONT4><NUTR_CONT5>30.71</NUTR_CONT5><NUTR_CONT6>230.56</NUTR_CONT6><NUTR_CONT7>30.72</NUTR_CONT7><NUTR_CONT8>5.36</NUTR_CONT8><NUTR_CONT9>0</NUTR_CONT9><BGN_YEAR>2017</BGN_YEAR><ANIMAL_PLANT>매일유업</ANIMAL_PLANT></item><item><DESC_KOR>바리스타카라멜딥프레소</DESC_KOR><SERVING_WT>200</SERVING_WT><NUTR_CONT1>122.84</NUTR_CONT1><NUTR_CONT2>19.2</NUTR_CONT2><NUTR_CONT3>3.08</NUTR_CONT3><NUTR_CONT4>3.84</NUTR_CONT4><NUTR_CONT5>19.2</NUTR_CONT5><NUTR_CONT6>107.48</NUTR_CONT6><NUTR_CONT7>15.36</NUTR_CONT7><NUTR_CONT8>2.68</NUTR_CONT8><NUTR_CONT9>0</NUTR_CONT9><BGN_YEAR>2015</BGN_YEAR><ANIMAL_PLANT>매일유업</ANIMAL_PLANT></item><item><DESC_KOR>바리스타카라멜딥프레소</DESC_KOR><SERVING_WT>200</SERVING_WT><NUTR_CONT1>245.68</NUTR_CONT1><NUTR_CONT2>38.4</NUTR_CONT2><NUTR_CONT3>6.16</NUTR_CONT3><NUTR_CONT4>7.68</NUTR_CONT4><NUTR_CONT5>40</NUTR_CONT5><NUTR_CONT6>214.96</NUTR_CONT6><NUTR_CONT7>30.72</NUTR_CONT7><NUTR_CONT8>5.36</NUTR_CONT8><NUTR_CONT9>0</NUTR_CONT9><BGN_YEAR>2017</BGN_YEAR><ANIMAL_PLANT>매일유업</ANIMAL_PLANT></item><item><DESC_KOR>바리스타카라멜바닐라라떼</DESC_KOR><SERVING_WT>200</SERVING_WT><NUTR_CONT1>115.28</NUTR_CONT1><NUTR_CONT2>16.9</NUTR_CONT2><NUTR_CONT3>3.08</NUTR_CONT3><NUTR_CONT4>3.84</NUTR_CONT4><NUTR_CONT5>16.9</NUTR_CONT5><NUTR_CONT6>99.9</NUTR_CONT6><NUTR_CONT7>15.36</NUTR_CONT7><NUTR_CONT8>2.3</NUTR_CONT8><NUTR_CONT9>0</NUTR_CONT9><BGN_YEAR>2015</BGN_YEAR><ANIMAL_PLANT>매일유업</ANIMAL_PLANT></item><item><DESC_KOR>바리스타카라멜바닐라라떼</DESC_KOR><SERVING_WT>200</SERVING_WT><NUTR_CONT1>230.56</NUTR_CONT1><NUTR_CONT2>33.8</NUTR_CONT2><NUTR_CONT3>6.16</NUTR_CONT3><NUTR_CONT4>7.68</NUTR_CONT4><NUTR_CONT5>30.71</NUTR_CONT5><NUTR_CONT6>199.8</NUTR_CONT6><NUTR_CONT7>30.72</NUTR_CONT7><NUTR_CONT8>4.6</NUTR_CONT8><NUTR_CONT9>0</NUTR_CONT9><BGN_YEAR>2017</BGN_YEAR><ANIMAL_PLANT>매일유업</ANIMAL_PLANT></item><item><DESC_KOR>바리스타로슈거에스프레소라떼</DESC_KOR><SERVING_WT>200</SERVING_WT><NUTR_CONT1>106.88</NUTR_CONT1><NUTR_CONT2>13.16</NUTR_CONT2><NUTR_CONT3>3.88</NUTR_CONT3><NUTR_CONT4>4.26</NUTR_CONT4><NUTR_CONT5>10.84</NUTR_CONT5><NUTR_CONT6>108.42</NUTR_CONT6><NUTR_CONT7>13.16</NUTR_CONT7><NUTR_CONT8>3.1</NUTR_CONT8><NUTR_CONT9>0</NUTR_CONT9><BGN_YEAR>2015</BGN_YEAR><ANIMAL_PLANT>매일유업</ANIMAL_PLANT></item><item><DESC_KOR>바리스타로슈거에스프레소라떼</DESC_KOR><SERVING_WT>200</SERVING_WT><NUTR_CONT1>213.76</NUTR_CONT1><NUTR_CONT2>26.32</NUTR_CONT2><NUTR_CONT3>7.76</NUTR_CONT3><NUTR_CONT4>8.52</NUTR_CONT4><NUTR_CONT5>22.4</NUTR_CONT5><NUTR_CONT6>216.84</NUTR_CONT6><NUTR_CONT7>26.32</NUTR_CONT7><NUTR_CONT8>6.2</NUTR_CONT8><NUTR_CONT9>0</NUTR_CONT9><BGN_YEAR>2017</BGN_YEAR><ANIMAL_PLANT>매일유업</ANIMAL_PLANT></item><item><DESC_KOR>우유속에딸기과즙</DESC_KOR><SERVING_WT>200</SERVING_WT><NUTR_CONT1>120</NUTR_CONT1><NUTR_CONT2>17</NUTR_CONT2><NUTR_CONT3>5</NUTR_CONT3><NUTR_CONT4>3.7</NUTR_CONT4><NUTR_CONT5>15</NUTR_CONT5><NUTR_CONT6>95</NUTR_CONT6><NUTR_CONT7>15</NUTR_CONT7><NUTR_CONT8>2.4</NUTR_CONT8><NUTR_CONT9>0</NUTR_CONT9><BGN_YEAR>2015</BGN_YEAR><ANIMAL_PLANT>매일유업</ANIMAL_PLANT></item><item><DESC_KOR>우유속에딸기과즙</DESC_KOR><SERVING_WT>200</SERVING_WT><NUTR_CONT1>240</NUTR_CONT1><NUTR_CONT2>34</NUTR_CONT2><NUTR_CONT3>10</NUTR_CONT3><NUTR_CONT4>7.4</NUTR_CONT4><NUTR_CONT5>37.98</NUTR_CONT5><NUTR_CONT6>190</NUTR_CONT6><NUTR_CONT7>30</NUTR_CONT7><NUTR_CONT8>4.8</NUTR_CONT8><NUTR_CONT9>0</NUTR_CONT9><BGN_YEAR>2017</BGN_YEAR><ANIMAL_PLANT>매일유업</ANIMAL_PLANT></item><item><DESC_KOR>우유속에바나나과즙</DESC_KOR><SERVING_WT>200</SERVING_WT><NUTR_CONT1>135</NUTR_CONT1><NUTR_CONT2>16.4</NUTR_CONT2><NUTR_CONT3>4.4</NUTR_CONT3><NUTR_CONT4>6</NUTR_CONT4><NUTR_CONT5>14</NUTR_CONT5><NUTR_CONT6>110</NUTR_CONT6><NUTR_CONT7>35</NUTR_CONT7><NUTR_CONT8>3.8</NUTR_CONT8><NUTR_CONT9>0</NUTR_CONT9><BGN_YEAR>2015</BGN_YEAR><ANIMAL_PLANT>매일유업</ANIMAL_PLANT></item><item><DESC_KOR>우유속에바나나과즙</DESC_KOR><SERVING_WT>200</SERVING_WT><NUTR_CONT1>270</NUTR_CONT1><NUTR_CONT2>32.8</NUTR_CONT2><NUTR_CONT3>8.8</NUTR_CONT3><NUTR_CONT4>12</NUTR_CONT4><NUTR_CONT5>28</NUTR_CONT5><NUTR_CONT6>220</NUTR_CONT6><NUTR_CONT7>70</NUTR_CONT7><NUTR_CONT8>7.6</NUTR_CONT8><NUTR_CONT9>0</NUTR_CONT9><BGN_YEAR>2017</BGN_YEAR><ANIMAL_PLANT>매일유업</ANIMAL_PLANT></item><item><DESC_KOR>우유속에코코아</DESC_KOR><SERVING_WT>200</SERVING_WT><NUTR_CONT1>135</NUTR_CONT1><NUTR_CONT2>18</NUTR_CONT2><NUTR_CONT3>5.2</NUTR_CONT3><NUTR_CONT4>4.6</NUTR_CONT4><NUTR_CONT5>13</NUTR_CONT5><NUTR_CONT6>110</NUTR_CONT6><NUTR_CONT7>25</NUTR_CONT7><NUTR_CONT8>3</NUTR_CONT8><NUTR_CONT9>0.2</NUTR_CONT9><BGN_YEAR>2015</BGN_YEAR><ANIMAL_PLANT>매일유업</ANIMAL_PLANT></item><item><DESC_KOR>우유속에코코아</DESC_KOR><SERVING_WT>200</SERVING_WT><NUTR_CONT1>270</NUTR_CONT1><NUTR_CONT2>36</NUTR_CONT2><NUTR_CONT3>10.4</NUTR_CONT3><NUTR_CONT4>9.2</NUTR_CONT4><NUTR_CONT5>40.93</NUTR_CONT5><NUTR_CONT6>220</NUTR_CONT6><NUTR_CONT7>50</NUTR_CONT7><NUTR_CONT8>6</NUTR_CONT8><NUTR_CONT9>0.4</NUTR_CONT9><BGN_YEAR>2017</BGN_YEAR><ANIMAL_PLANT>매일유업</ANIMAL_PLANT></item><item><DESC_KOR>우유속에마끼아또커피</DESC_KOR><SERVING_WT>200</SERVING_WT><NUTR_CONT1>126.5</NUTR_CONT1><NUTR_CONT2>18</NUTR_CONT2><NUTR_CONT3>3.5</NUTR_CONT3><NUTR_CONT4>4.5</NUTR_CONT4><NUTR_CONT5>18</NUTR_CONT5><NUTR_CONT6>100</NUTR_CONT6><NUTR_CONT7>15</NUTR_CONT7><NUTR_CONT8>2.7</NUTR_CONT8><NUTR_CONT9>0</NUTR_CONT9><BGN_YEAR>2015</BGN_YEAR><ANIMAL_PLANT>매일유업</ANIMAL_PLANT></item><item><DESC_KOR>우유속에마끼아또커피</DESC_KOR><SERVING_WT>200</SERVING_WT><NUTR_CONT1>253</NUTR_CONT1><NUTR_CONT2>36</NUTR_CONT2><NUTR_CONT3>7</NUTR_CONT3><NUTR_CONT4>9</NUTR_CONT4><NUTR_CONT5>33.66</NUTR_CONT5><NUTR_CONT6>200</NUTR_CONT6><NUTR_CONT7>30</NUTR_CONT7><NUTR_CONT8>5.4</NUTR_CONT8><NUTR_CONT9>0</NUTR_CONT9><BGN_YEAR>2017</BGN_YEAR><ANIMAL_PLANT>매일유업</ANIMAL_PLANT></item><item><DESC_KOR>우유속에모카치노커피</DESC_KOR><SERVING_WT>200</SERVING_WT><NUTR_CONT1>133</NUTR_CONT1><NUTR_CONT2>18</NUTR_CONT2><NUTR_CONT3>4</NUTR_CONT3><NUTR_CONT4>5</NUTR_CONT4><NUTR_CONT5>18</NUTR_CONT5><NUTR_CONT6>110</NUTR_CONT6><NUTR_CONT7>20</NUTR_CONT7><NUTR_CONT8>3.5</NUTR_CONT8><NUTR_CONT9>0</NUTR_CONT9><BGN_YEAR>2015</BGN_YEAR><ANIMAL_PLANT>매일유업</ANIMAL_PLANT></item><item><DESC_KOR>우유속에모카치노커피</DESC_KOR><SERVING_WT>200</SERVING_WT><NUTR_CONT1>266</NUTR_CONT1><NUTR_CONT2>36</NUTR_CONT2><NUTR_CONT3>8</NUTR_CONT3><NUTR_CONT4>10</NUTR_CONT4><NUTR_CONT5>33.66</NUTR_CONT5><NUTR_CONT6>220</NUTR_CONT6><NUTR_CONT7>40</NUTR_CONT7><NUTR_CONT8>7</NUTR_CONT8><NUTR_CONT9>0</NUTR_CONT9><BGN_YEAR>2017</BGN_YEAR><ANIMAL_PLANT>매일유업</ANIMAL_PLANT></item><item><DESC_KOR>우유속에에스프레소커피</DESC_KOR><SERVING_WT>200</SERVING_WT><NUTR_CONT1>133</NUTR_CONT1><NUTR_CONT2>18</NUTR_CONT2><NUTR_CONT3>4</NUTR_CONT3><NUTR_CONT4>5</NUTR_CONT4><NUTR_CONT5>18</NUTR_CONT5><NUTR_CONT6>115</NUTR_CONT6><NUTR_CONT7>20</NUTR_CONT7><NUTR_CONT8>3.3</NUTR_CONT8><NUTR_CONT9>0</NUTR_CONT9><BGN_YEAR>2015</BGN_YEAR><ANIMAL_PLANT>매일유업</ANIMAL_PLANT></item><item><DESC_KOR>우유속에에스프레소커피</DESC_KOR><SERVING_WT>200</SERVING_WT><NUTR_CONT1>266</NUTR_CONT1><NUTR_CONT2>36</NUTR_CONT2><NUTR_CONT3>8</NUTR_CONT3><NUTR_CONT4>10</NUTR_CONT4><NUTR_CONT5>33.66</NUTR_CONT5><NUTR_CONT6>230</NUTR_CONT6><NUTR_CONT7>40</NUTR_CONT7><NUTR_CONT8>6.6</NUTR_CONT8><NUTR_CONT9>0</NUTR_CONT9><BGN_YEAR>2017</BGN_YEAR><ANIMAL_PLANT>매일유업</ANIMAL_PLANT></item><item><DESC_KOR>매일우유딸기</DESC_KOR><SERVING_WT>200</SERVING_WT><NUTR_CONT1>135</NUTR_CONT1><NUTR_CONT2>22</NUTR_CONT2><NUTR_CONT3>4</NUTR_CONT3><NUTR_CONT4>3.2</NUTR_CONT4><NUTR_CONT5>22</NUTR_CONT5><NUTR_CONT6>110</NUTR_CONT6><NUTR_CONT7>15</NUTR_CONT7><NUTR_CONT8>2.1</NUTR_CONT8><NUTR_CONT9>0</NUTR_CONT9><BGN_YEAR>2015</BGN_YEAR><ANIMAL_PLANT>매일유업</ANIMAL_PLANT></item><item><DESC_KOR>매일우유딸기</DESC_KOR><SERVING_WT>200</SERVING_WT><NUTR_CONT1>270</NUTR_CONT1><NUTR_CONT2>44</NUTR_CONT2><NUTR_CONT3>8</NUTR_CONT3><NUTR_CONT4>6.4</NUTR_CONT4><NUTR_CONT5>37.98</NUTR_CONT5><NUTR_CONT6>220</NUTR_CONT6><NUTR_CONT7>30</NUTR_CONT7><NUTR_CONT8>4.2</NUTR_CONT8><NUTR_CONT9>0</NUTR_CONT9><BGN_YEAR>2017</BGN_YEAR><ANIMAL_PLANT>매일유업</ANIMAL_PLANT></item><item><DESC_KOR>매일우유초콜릿</DESC_KOR><SERVING_WT>200</SERVING_WT><NUTR_CONT1>120</NUTR_CONT1><NUTR_CONT2>15</NUTR_CONT2><NUTR_CONT3>6</NUTR_CONT3><NUTR_CONT4>3.8</NUTR_CONT4><NUTR_CONT5>13</NUTR_CONT5><NUTR_CONT6>120</NUTR_CONT6><NUTR_CONT7>15</NUTR_CONT7><NUTR_CONT8>2.4</NUTR_CONT8><NUTR_CONT9>0</NUTR_CONT9><BGN_YEAR>2015</BGN_YEAR><ANIMAL_PLANT>매일유업</ANIMAL_PLANT></item><item><DESC_KOR>매일우유초콜릿</DESC_KOR><SERVING_WT>200</SERVING_WT><NUTR_CONT1>240</NUTR_CONT1><NUTR_CONT2>30</NUTR_CONT2><NUTR_CONT3>12</NUTR_CONT3><NUTR_CONT4>7.6</NUTR_CONT4><NUTR_CONT5>38</NUTR_CONT5><NUTR_CONT6>240</NUTR_CONT6><NUTR_CONT7>30</NUTR_CONT7><NUTR_CONT8>4.8</NUTR_CONT8><NUTR_CONT9>0</NUTR_CONT9><BGN_YEAR>2017</BGN_YEAR><ANIMAL_PLANT>매일유업</ANIMAL_PLANT></item><item><DESC_KOR>매일우유커피</DESC_KOR><SERVING_WT>200</SERVING_WT><NUTR_CONT1>120.2</NUTR_CONT1><NUTR_CONT2>18</NUTR_CONT2><NUTR_CONT3>4.4</NUTR_CONT3><NUTR_CONT4>3.4</NUTR_CONT4><NUTR_CONT5>18</NUTR_CONT5><NUTR_CONT6>110</NUTR_CONT6><NUTR_CONT7>15</NUTR_CONT7><NUTR_CONT8>2</NUTR_CONT8><NUTR_CONT9>0</NUTR_CONT9><BGN_YEAR>2015</BGN_YEAR><ANIMAL_PLANT>매일유업</ANIMAL_PLANT></item><item><DESC_KOR>매일우유커피</DESC_KOR><SERVING_WT>200</SERVING_WT><NUTR_CONT1>240.4</NUTR_CONT1><NUTR_CONT2>36</NUTR_CONT2><NUTR_CONT3>8.8</NUTR_CONT3><NUTR_CONT4>6.8</NUTR_CONT4><NUTR_CONT5>33.66</NUTR_CONT5><NUTR_CONT6>220</NUTR_CONT6><NUTR_CONT7>30</NUTR_CONT7><NUTR_CONT8>4</NUTR_CONT8><NUTR_CONT9>0</NUTR_CONT9><BGN_YEAR>2017</BGN_YEAR><ANIMAL_PLANT>매일유업</ANIMAL_PLANT></item><item><DESC_KOR>매일우유검은콩</DESC_KOR><SERVING_WT>200</SERVING_WT><NUTR_CONT1>118</NUTR_CONT1><NUTR_CONT2>36.2</NUTR_CONT2><NUTR_CONT3>4.3</NUTR_CONT3><NUTR_CONT4>3.2</NUTR_CONT4><NUTR_CONT5>35.2</NUTR_CONT5><NUTR_CONT6>80</NUTR_CONT6><NUTR_CONT7>20</NUTR_CONT7><NUTR_CONT8>1.8</NUTR_CONT8><NUTR_CONT9>0</NUTR_CONT9><BGN_YEAR>2015</BGN_YEAR><ANIMAL_PLANT>매일유업</ANIMAL_PLANT></item><item><DESC_KOR>매일우유검은콩</DESC_KOR><SERVING_WT>200</SERVING_WT><NUTR_CONT1>236</NUTR_CONT1><NUTR_CONT2>72.4</NUTR_CONT2><NUTR_CONT3>8.6</NUTR_CONT3><NUTR_CONT4>6.4</NUTR_CONT4><NUTR_CONT5>37.78</NUTR_CONT5><NUTR_CONT6>160</NUTR_CONT6><NUTR_CONT7>40</NUTR_CONT7><NUTR_CONT8>3.6</NUTR_CONT8><NUTR_CONT9>0</NUTR_CONT9><BGN_YEAR>2017</BGN_YEAR><ANIMAL_PLANT>매일유업</ANIMAL_PLANT></item><item><DESC_KOR>매일우유딸기(멸균)</DESC_KOR><SERVING_WT>200</SERVING_WT><NUTR_CONT1>135</NUTR_CONT1><NUTR_CONT2>44</NUTR_CONT2><NUTR_CONT3>4</NUTR_CONT3><NUTR_CONT4>3.2</NUTR_CONT4><NUTR_CONT5>44</NUTR_CONT5><NUTR_CONT6>110</NUTR_CONT6><NUTR_CONT7>15</NUTR_CONT7><NUTR_CONT8>2.1</NUTR_CONT8><NUTR_CONT9>0</NUTR_CONT9><BGN_YEAR>2015</BGN_YEAR><ANIMAL_PLANT>매일유업</ANIMAL_PLANT></item><item><DESC_KOR>매일우유딸기(멸균)</DESC_KOR><SERVING_WT>200</SERVING_WT><NUTR_CONT1>270</NUTR_CONT1><NUTR_CONT2>88</NUTR_CONT2><NUTR_CONT3>8</NUTR_CONT3><NUTR_CONT4>6.4</NUTR_CONT4><NUTR_CONT5>88</NUTR_CONT5><NUTR_CONT6>220</NUTR_CONT6><NUTR_CONT7>30</NUTR_CONT7><NUTR_CONT8>4.2</NUTR_CONT8><NUTR_CONT9>0</NUTR_CONT9><BGN_YEAR>2017</BGN_YEAR><ANIMAL_PLANT>매일유업</ANIMAL_PLANT></item><item><DESC_KOR>매일우유초콜릿(멸균)</DESC_KOR><SERVING_WT>200</SERVING_WT><NUTR_CONT1>130</NUTR_CONT1><NUTR_CONT2>22</NUTR_CONT2><NUTR_CONT3>5</NUTR_CONT3><NUTR_CONT4>2.6</NUTR_CONT4><NUTR_CONT5>42</NUTR_CONT5><NUTR_CONT6>65</NUTR_CONT6><NUTR_CONT7>10</NUTR_CONT7><NUTR_CONT8>1.6</NUTR_CONT8><NUTR_CONT9>0</NUTR_CONT9><BGN_YEAR>2015</BGN_YEAR><ANIMAL_PLANT>매일유업</ANIMAL_PLANT></item><item><DESC_KOR>매일우유초콜릿(멸균)</DESC_KOR><SERVING_WT>200</SERVING_WT><NUTR_CONT1>260</NUTR_CONT1><NUTR_CONT2>44</NUTR_CONT2><NUTR_CONT3>10</NUTR_CONT3><NUTR_CONT4>5.2</NUTR_CONT4><NUTR_CONT5>38</NUTR_CONT5><NUTR_CONT6>130</NUTR_CONT6><NUTR_CONT7>20</NUTR_CONT7><NUTR_CONT8>3.2</NUTR_CONT8><NUTR_CONT9>0</NUTR_CONT9><BGN_YEAR>2017</BGN_YEAR><ANIMAL_PLANT>매일유업</ANIMAL_PLANT></item><item><DESC_KOR>허쉬초콜릿드링크</DESC_KOR><SERVING_WT>100</SERVING_WT><NUTR_CONT1>66.57</NUTR_CONT1><NUTR_CONT2>12.34</NUTR_CONT2><NUTR_CONT3>2.3</NUTR_CONT3><NUTR_CONT4>0.89</NUTR_CONT4><NUTR_CONT5>11.91</NUTR_CONT5><NUTR_CONT6>46.8</NUTR_CONT6><NUTR_CONT7>1.28</NUTR_CONT7><NUTR_CONT8>0.21</NUTR_CONT8><NUTR_CONT9>0.43</NUTR_CONT9><BGN_YEAR>2015</BGN_YEAR><ANIMAL_PLANT>매일유업</ANIMAL_PLANT></item><item><DESC_KOR>허쉬초콜릿드링크</DESC_KOR><SERVING_WT>100</SERVING_WT><NUTR_CONT1>66.57</NUTR_CONT1><NUTR_CONT2>12.34</NUTR_CONT2><NUTR_CONT3>2.3</NUTR_CONT3><NUTR_CONT4>0.89</NUTR_CONT4><NUTR_CONT5>12.63</NUTR_CONT5><NUTR_CONT6>46.8</NUTR_CONT6><NUTR_CONT7>1.28</NUTR_CONT7><NUTR_CONT8>0.21</NUTR_CONT8><NUTR_CONT9>0.43</NUTR_CONT9><BGN_YEAR>2017</BGN_YEAR><ANIMAL_PLANT>매일유업</ANIMAL_PLANT></item><item><DESC_KOR>허쉬초콜릿드링크밀크초콜릿</DESC_KOR><SERVING_WT>100</SERVING_WT><NUTR_CONT1>71.31</NUTR_CONT1><NUTR_CONT2>11.49</NUTR_CONT2><NUTR_CONT3>2.13</NUTR_CONT3><NUTR_CONT4>1.87</NUTR_CONT4><NUTR_CONT5>9.79</NUTR_CONT5><NUTR_CONT6>42.55</NUTR_CONT6><NUTR_CONT7>5.11</NUTR_CONT7><NUTR_CONT8>0.85</NUTR_CONT8><NUTR_CONT9>0.43</NUTR_CONT9><BGN_YEAR>2015</BGN_YEAR><ANIMAL_PLANT>매일유업</ANIMAL_PLANT></item><item><DESC_KOR>허쉬초콜릿드링크밀크초콜릿</DESC_KOR><SERVING_WT>100</SERVING_WT><NUTR_CONT1>71.31</NUTR_CONT1><NUTR_CONT2>11.49</NUTR_CONT2><NUTR_CONT3>2.13</NUTR_CONT3><NUTR_CONT4>1.87</NUTR_CONT4><NUTR_CONT5>12.63</NUTR_CONT5><NUTR_CONT6>42.55</NUTR_CONT6><NUTR_CONT7>5.11</NUTR_CONT7><NUTR_CONT8>0.85</NUTR_CONT8><NUTR_CONT9>0.43</NUTR_CONT9><BGN_YEAR>2017</BGN_YEAR><ANIMAL_PLANT>매일유업</ANIMAL_PLANT></item><item><DESC_KOR>허쉬초콜릿드링크쿠키＇앤＇크림</DESC_KOR><SERVING_WT>100</SERVING_WT><NUTR_CONT1>72.85</NUTR_CONT1><NUTR_CONT2>11.91</NUTR_CONT2><NUTR_CONT3>2.77</NUTR_CONT3><NUTR_CONT4>1.57</NUTR_CONT4><NUTR_CONT5>11.06</NUTR_CONT5><NUTR_CONT6>51.06</NUTR_CONT6><NUTR_CONT7>2.13</NUTR_CONT7><NUTR_CONT8>0.51</NUTR_CONT8><NUTR_CONT9>0.51</NUTR_CONT9><BGN_YEAR>2015</BGN_YEAR><ANIMAL_PLANT>매일유업</ANIMAL_PLANT></item><item><DESC_KOR>허쉬초콜릿드링크쿠키＇앤＇크림</DESC_KOR><SERVING_WT>100</SERVING_WT><NUTR_CONT1>72.85</NUTR_CONT1><NUTR_CONT2>11.91</NUTR_CONT2><NUTR_CONT3>2.77</NUTR_CONT3><NUTR_CONT4>1.57</NUTR_CONT4><NUTR_CONT5>12.63</NUTR_CONT5><NUTR_CONT6>51.06</NUTR_CONT6><NUTR_CONT7>2.13</NUTR_CONT7><NUTR_CONT8>0.51</NUTR_CONT8><NUTR_CONT9>0.51</NUTR_CONT9><BGN_YEAR>2017</BGN_YEAR><ANIMAL_PLANT>매일유업</ANIMAL_PLANT></item><item><DESC_KOR>바나나는원래하얗다</DESC_KOR><SERVING_WT>100</SERVING_WT><NUTR_CONT1>62.5</NUTR_CONT1><NUTR_CONT2>9.58</NUTR_CONT2><NUTR_CONT3>2.08</NUTR_CONT3><NUTR_CONT4>1.71</NUTR_CONT4><NUTR_CONT5>9.58</NUTR_CONT5><NUTR_CONT6>58.33</NUTR_CONT6><NUTR_CONT7>6.25</NUTR_CONT7><NUTR_CONT8>1.13</NUTR_CONT8><NUTR_CONT9>0</NUTR_CONT9><BGN_YEAR>2015</BGN_YEAR><ANIMAL_PLANT>매일유업</ANIMAL_PLANT></item><item><DESC_KOR>상하목장유기농딸기우유</DESC_KOR><SERVING_WT>200</SERVING_WT><NUTR_CONT1>168</NUTR_CONT1><NUTR_CONT2>20.8</NUTR_CONT2><NUTR_CONT3>7</NUTR_CONT3><NUTR_CONT4>9</NUTR_CONT4><NUTR_CONT5>26</NUTR_CONT5><NUTR_CONT6>120</NUTR_CONT6><NUTR_CONT7>36</NUTR_CONT7><NUTR_CONT8>6</NUTR_CONT8><NUTR_CONT9>0</NUTR_CONT9><BGN_YEAR>2015</BGN_YEAR><ANIMAL_PLANT>매일유업</ANIMAL_PLANT></item><item><DESC_KOR>상하목장유기농딸기우유</DESC_KOR><SERVING_WT>200</SERVING_WT><NUTR_CONT1>336</NUTR_CONT1><NUTR_CONT2>41.6</NUTR_CONT2><NUTR_CONT3>14</NUTR_CONT3><NUTR_CONT4>18</NUTR_CONT4><NUTR_CONT5>37.98</NUTR_CONT5><NUTR_CONT6>240</NUTR_CONT6><NUTR_CONT7>72</NUTR_CONT7><NUTR_CONT8>12</NUTR_CONT8><NUTR_CONT9>0</NUTR_CONT9><BGN_YEAR>2017</BGN_YEAR><ANIMAL_PLANT>매일유업</ANIMAL_PLANT></item><item><DESC_KOR>상하목장유기농바나나우유</DESC_KOR><SERVING_WT>200</SERVING_WT><NUTR_CONT1>176</NUTR_CONT1><NUTR_CONT2>21.6</NUTR_CONT2><NUTR_CONT3>5.6</NUTR_CONT3><NUTR_CONT4>4.8</NUTR_CONT4><NUTR_CONT5>21.6</NUTR_CONT5><NUTR_CONT6>96</NUTR_CONT6><NUTR_CONT7>28.8</NUTR_CONT7><NUTR_CONT8>4.8</NUTR_CONT8><NUTR_CONT9>0</NUTR_CONT9><BGN_YEAR>2015</BGN_YEAR><ANIMAL_PLANT>매일유업</ANIMAL_PLANT></item><item><DESC_KOR>상하목장유기농바나나우유</DESC_KOR><SERVING_WT>200</SERVING_WT><NUTR_CONT1>352</NUTR_CONT1><NUTR_CONT2>43.2</NUTR_CONT2><NUTR_CONT3>11.2</NUTR_CONT3><NUTR_CONT4>9.6</NUTR_CONT4><NUTR_CONT5>40.44</NUTR_CONT5><NUTR_CONT6>192</NUTR_CONT6><NUTR_CONT7>57.6</NUTR_CONT7><NUTR_CONT8>9.6</NUTR_CONT8><NUTR_CONT9>0</NUTR_CONT9><BGN_YEAR>2017</BGN_YEAR><ANIMAL_PLANT>매일유업</ANIMAL_PLANT></item><item><DESC_KOR>상하목장유기농코코아우유</DESC_KOR><SERVING_WT>200</SERVING_WT><NUTR_CONT1>176</NUTR_CONT1><NUTR_CONT2>24</NUTR_CONT2><NUTR_CONT3>6.08</NUTR_CONT3><NUTR_CONT4>5.6</NUTR_CONT4><NUTR_CONT5>22.4</NUTR_CONT5><NUTR_CONT6>96</NUTR_CONT6><NUTR_CONT7>24</NUTR_CONT7><NUTR_CONT8>4</NUTR_CONT8><NUTR_CONT9>0</NUTR_CONT9><BGN_YEAR>2015</BGN_YEAR><ANIMAL_PLANT>매일유업</ANIMAL_PLANT></item><item><DESC_KOR>상하목장유기농코코아우유</DESC_KOR><SERVING_WT>200</SERVING_WT><NUTR_CONT1>352</NUTR_CONT1><NUTR_CONT2>48</NUTR_CONT2><NUTR_CONT3>12.16</NUTR_CONT3><NUTR_CONT4>11.2</NUTR_CONT4><NUTR_CONT5>38</NUTR_CONT5><NUTR_CONT6>192</NUTR_CONT6><NUTR_CONT7>48</NUTR_CONT7><NUTR_CONT8>8</NUTR_CONT8><NUTR_CONT9>0</NUTR_CONT9><BGN_YEAR>2017</BGN_YEAR><ANIMAL_PLANT>매일유업</ANIMAL_PLANT></item><item><DESC_KOR>(올가)유기바나나우유</DESC_KOR><SERVING_WT>200</SERVING_WT><NUTR_CONT1>184</NUTR_CONT1><NUTR_CONT2>24</NUTR_CONT2><NUTR_CONT3>8</NUTR_CONT3><NUTR_CONT4>7.36</NUTR_CONT4><NUTR_CONT5>30</NUTR_CONT5><NUTR_CONT6>96</NUTR_CONT6><NUTR_CONT7>24</NUTR_CONT7><NUTR_CONT8>4.48</NUTR_CONT8><NUTR_CONT9>0</NUTR_CONT9><BGN_YEAR>2015</BGN_YEAR><ANIMAL_PLANT>매일유업</ANIMAL_PLANT></item><item><DESC_KOR>(올가)유기바나나우유</DESC_KOR><SERVING_WT>200</SERVING_WT><NUTR_CONT1>368</NUTR_CONT1><NUTR_CONT2>48</NUTR_CONT2><NUTR_CONT3>16</NUTR_CONT3><NUTR_CONT4>14.72</NUTR_CONT4><NUTR_CONT5>40.44</NUTR_CONT5><NUTR_CONT6>192</NUTR_CONT6><NUTR_CONT7>48</NUTR_CONT7><NUTR_CONT8>8.96</NUTR_CONT8><NUTR_CONT9>0</NUTR_CONT9><BGN_YEAR>2017</BGN_YEAR><ANIMAL_PLANT>매일유업</ANIMAL_PLANT></item><item><DESC_KOR>(올가)유기딸기우유</DESC_KOR><SERVING_WT>200</SERVING_WT><NUTR_CONT1>240</NUTR_CONT1><NUTR_CONT2>30</NUTR_CONT2><NUTR_CONT3>6.4</NUTR_CONT3><NUTR_CONT4>7.84</NUTR_CONT4><NUTR_CONT5>22.4</NUTR_CONT5><NUTR_CONT6>96</NUTR_CONT6><NUTR_CONT7>24</NUTR_CONT7><NUTR_CONT8>4.8</NUTR_CONT8><NUTR_CONT9>0</NUTR_CONT9><BGN_YEAR>2015</BGN_YEAR><ANIMAL_PLANT>매일유업</ANIMAL_PLANT></item><item><DESC_KOR>(올가)유기딸기우유</DESC_KOR><SERVING_WT>200</SERVING_WT><NUTR_CONT1>480</NUTR_CONT1><NUTR_CONT2>60</NUTR_CONT2><NUTR_CONT3>12.8</NUTR_CONT3><NUTR_CONT4>15.68</NUTR_CONT4><NUTR_CONT5>37.98</NUTR_CONT5><NUTR_CONT6>192</NUTR_CONT6><NUTR_CONT7>48</NUTR_CONT7><NUTR_CONT8>9.6</NUTR_CONT8><NUTR_CONT9>0</NUTR_CONT9><BGN_YEAR>2017</BGN_YEAR><ANIMAL_PLANT>매일유업</ANIMAL_PLANT></item><item><DESC_KOR>(초록마을)유기농바나나우유</DESC_KOR><SERVING_WT>200</SERVING_WT><NUTR_CONT1>220</NUTR_CONT1><NUTR_CONT2>27</NUTR_CONT2><NUTR_CONT3>5.6</NUTR_CONT3><NUTR_CONT4>7.2</NUTR_CONT4><NUTR_CONT5>21.6</NUTR_CONT5><NUTR_CONT6>96</NUTR_CONT6><NUTR_CONT7>28.8</NUTR_CONT7><NUTR_CONT8>4.8</NUTR_CONT8><NUTR_CONT9>0</NUTR_CONT9><BGN_YEAR>2015</BGN_YEAR><ANIMAL_PLANT>매일유업</ANIMAL_PLANT></item><item><DESC_KOR>(초록마을)유기농바나나우유</DESC_KOR><SERVING_WT>200</SERVING_WT><NUTR_CONT1>440</NUTR_CONT1><NUTR_CONT2>54</NUTR_CONT2><NUTR_CONT3>11.2</NUTR_CONT3><NUTR_CONT4>14.4</NUTR_CONT4><NUTR_CONT5>40.44</NUTR_CONT5><NUTR_CONT6>192</NUTR_CONT6><NUTR_CONT7>57.6</NUTR_CONT7><NUTR_CONT8>9.6</NUTR_CONT8><NUTR_CONT9>0</NUTR_CONT9><BGN_YEAR>2017</BGN_YEAR><ANIMAL_PLANT>매일유업</ANIMAL_PLANT></item><item><DESC_KOR>(초록마을)유기농딸기우유</DESC_KOR><SERVING_WT>200</SERVING_WT><NUTR_CONT1>168</NUTR_CONT1><NUTR_CONT2>20.8</NUTR_CONT2><NUTR_CONT3>5.6</NUTR_CONT3><NUTR_CONT4>9</NUTR_CONT4><NUTR_CONT5>20.8</NUTR_CONT5><NUTR_CONT6>120</NUTR_CONT6><NUTR_CONT7>36</NUTR_CONT7><NUTR_CONT8>6</NUTR_CONT8><NUTR_CONT9>0</NUTR_CONT9><BGN_YEAR>2015</BGN_YEAR><ANIMAL_PLANT>매일유업</ANIMAL_PLANT></item><item><DESC_KOR>(초록마을)유기농딸기우유</DESC_KOR><SERVING_WT>200</SERVING_WT><NUTR_CONT1>336</NUTR_CONT1><NUTR_CONT2>41.6</NUTR_CONT2><NUTR_CONT3>11.2</NUTR_CONT3><NUTR_CONT4>18</NUTR_CONT4><NUTR_CONT5>37.98</NUTR_CONT5><NUTR_CONT6>240</NUTR_CONT6><NUTR_CONT7>72</NUTR_CONT7><NUTR_CONT8>12</NUTR_CONT8><NUTR_CONT9>0</NUTR_CONT9><BGN_YEAR>2017</BGN_YEAR><ANIMAL_PLANT>매일유업</ANIMAL_PLANT></item><item><DESC_KOR>(푸드머스)바나나라떼</DESC_KOR><SERVING_WT>200</SERVING_WT><NUTR_CONT1>160</NUTR_CONT1><NUTR_CONT2>22.4</NUTR_CONT2><NUTR_CONT3>6.4</NUTR_CONT3><NUTR_CONT4>4.8</NUTR_CONT4><NUTR_CONT5>20.8</NUTR_CONT5><NUTR_CONT6>88</NUTR_CONT6><NUTR_CONT7>16</NUTR_CONT7><NUTR_CONT8>2.88</NUTR_CONT8><NUTR_CONT9>0</NUTR_CONT9><BGN_YEAR>2015</BGN_YEAR><ANIMAL_PLANT>매일유업</ANIMAL_PLANT></item><item><DESC_KOR>(푸드머스)바나나라떼</DESC_KOR><SERVING_WT>200</SERVING_WT><NUTR_CONT1>320</NUTR_CONT1><NUTR_CONT2>44.8</NUTR_CONT2><NUTR_CONT3>12.8</NUTR_CONT3><NUTR_CONT4>9.6</NUTR_CONT4><NUTR_CONT5>40.44</NUTR_CONT5><NUTR_CONT6>176</NUTR_CONT6><NUTR_CONT7>32</NUTR_CONT7><NUTR_CONT8>5.76</NUTR_CONT8><NUTR_CONT9>0</NUTR_CONT9><BGN_YEAR>2017</BGN_YEAR><ANIMAL_PLANT>매일유업</ANIMAL_PLANT></item><item><DESC_KOR>후레쉬초콜릿밀크</DESC_KOR><SERVING_WT>200</SERVING_WT><NUTR_CONT1>115</NUTR_CONT1><NUTR_CONT2>42</NUTR_CONT2><NUTR_CONT3>5</NUTR_CONT3><NUTR_CONT4>1.5</NUTR_CONT4><NUTR_CONT5>40</NUTR_CONT5><NUTR_CONT6>90</NUTR_CONT6><NUTR_CONT7>5</NUTR_CONT7><NUTR_CONT8>0.9</NUTR_CONT8><NUTR_CONT9>0</NUTR_CONT9><BGN_YEAR>2015</BGN_YEAR><ANIMAL_PLANT>매일유업</ANIMAL_PLANT></item><item><DESC_KOR>후레쉬초콜릿밀크</DESC_KOR><SERVING_WT>200</SERVING_WT><NUTR_CONT1>230</NUTR_CONT1><NUTR_CONT2>84</NUTR_CONT2><NUTR_CONT3>10</NUTR_CONT3><NUTR_CONT4>3</NUTR_CONT4><NUTR_CONT5>190.3</NUTR_CONT5><NUTR_CONT6>180</NUTR_CONT6><NUTR_CONT7>10</NUTR_CONT7><NUTR_CONT8>1.8</NUTR_CONT8><NUTR_CONT9>0</NUTR_CONT9><BGN_YEAR>2017</BGN_YEAR><ANIMAL_PLANT>매일유업</ANIMAL_PLANT></item><item><DESC_KOR>(CU)CU메론우유</DESC_KOR><SERVING_WT>200</SERVING_WT><NUTR_CONT1>130</NUTR_CONT1><NUTR_CONT2>16</NUTR_CONT2><NUTR_CONT3>4.2</NUTR_CONT3><NUTR_CONT4>5.4</NUTR_CONT4><NUTR_CONT5>15</NUTR_CONT5><NUTR_CONT6>80</NUTR_CONT6><NUTR_CONT7>30</NUTR_CONT7><NUTR_CONT8>3.5</NUTR_CONT8><NUTR_CONT9>0</NUTR_CONT9><BGN_YEAR>2015</BGN_YEAR><ANIMAL_PLANT>매일유업</ANIMAL_PLANT></item><item><DESC_KOR>(CU)CU메론우유</DESC_KOR><SERVING_WT>200</SERVING_WT><NUTR_CONT1>260</NUTR_CONT1><NUTR_CONT2>32</NUTR_CONT2><NUTR_CONT3>8.4</NUTR_CONT3><NUTR_CONT4>10.8</NUTR_CONT4><NUTR_CONT5>30</NUTR_CONT5><NUTR_CONT6>160</NUTR_CONT6><NUTR_CONT7>60</NUTR_CONT7><NUTR_CONT8>7</NUTR_CONT8><NUTR_CONT9>0</NUTR_CONT9><BGN_YEAR>2017</BGN_YEAR><ANIMAL_PLANT>매일유업</ANIMAL_PLANT></item><item><DESC_KOR>(CU)CU커피우유</DESC_KOR><SERVING_WT>200</SERVING_WT><NUTR_CONT1>114.4</NUTR_CONT1><NUTR_CONT2>16</NUTR_CONT2><NUTR_CONT3>3.6</NUTR_CONT3><NUTR_CONT4>4</NUTR_CONT4><NUTR_CONT5>14</NUTR_CONT5><NUTR_CONT6>100</NUTR_CONT6><NUTR_CONT7>15</NUTR_CONT7><NUTR_CONT8>3</NUTR_CONT8><NUTR_CONT9>0</NUTR_CONT9><BGN_YEAR>2015</BGN_YEAR><ANIMAL_PLANT>매일유업</ANIMAL_PLANT></item><item><DESC_KOR>(CU)CU커피우유</DESC_KOR><SERVING_WT>200</SERVING_WT><NUTR_CONT1>228.8</NUTR_CONT1><NUTR_CONT2>32</NUTR_CONT2><NUTR_CONT3>7.2</NUTR_CONT3><NUTR_CONT4>8</NUTR_CONT4><NUTR_CONT5>33.66</NUTR_CONT5><NUTR_CONT6>200</NUTR_CONT6><NUTR_CONT7>30</NUTR_CONT7><NUTR_CONT8>6</NUTR_CONT8><NUTR_CONT9>0</NUTR_CONT9><BGN_YEAR>2017</BGN_YEAR><ANIMAL_PLANT>매일유업</ANIMAL_PLANT></item><item><DESC_KOR>매일우유저지방&amp;고칼슘1%</DESC_KOR><SERVING_WT>200</SERVING_WT><NUTR_CONT1>80</NUTR_CONT1><NUTR_CONT2>10</NUTR_CONT2><NUTR_CONT3>6</NUTR_CONT3><NUTR_CONT4>2</NUTR_CONT4><NUTR_CONT5>9</NUTR_CONT5><NUTR_CONT6>100</NUTR_CONT6><NUTR_CONT7>7.4</NUTR_CONT7><NUTR_CONT8>1.2</NUTR_CONT8><NUTR_CONT9>0</NUTR_CONT9><BGN_YEAR>2015</BGN_YEAR><ANIMAL_PLANT>매일유업</ANIMAL_PLANT></item><item><DESC_KOR>매일우유저지방&amp;고칼슘1%</DESC_KOR><SERVING_WT>200</SERVING_WT><NUTR_CONT1>160</NUTR_CONT1><NUTR_CONT2>20</NUTR_CONT2><NUTR_CONT3>12</NUTR_CONT3><NUTR_CONT4>4</NUTR_CONT4><NUTR_CONT5>18</NUTR_CONT5><NUTR_CONT6>200</NUTR_CONT6><NUTR_CONT7>14.8</NUTR_CONT7><NUTR_CONT8>2.4</NUTR_CONT8><NUTR_CONT9>0</NUTR_CONT9><BGN_YEAR>2017</BGN_YEAR><ANIMAL_PLANT>매일유업</ANIMAL_PLANT></item><item><DESC_KOR>매일우유무지방&amp;고칼슘0%</DESC_KOR><SERVING_WT>200</SERVING_WT><NUTR_CONT1>60</NUTR_CONT1><NUTR_CONT2>10</NUTR_CONT2><NUTR_CONT3>6</NUTR_CONT3><NUTR_CONT4>0</NUTR_CONT4><NUTR_CONT5>9</NUTR_CONT5><NUTR_CONT6>100</NUTR_CONT6><NUTR_CONT7>0</NUTR_CONT7><NUTR_CONT8>0</NUTR_CONT8><NUTR_CONT9>0</NUTR_CONT9><BGN_YEAR>2015</BGN_YEAR><ANIMAL_PLANT>매일유업</ANIMAL_PLANT></item><item><DESC_KOR>매일우유무지방&amp;고칼슘0%</DESC_KOR><SERVING_WT>200</SERVING_WT><NUTR_CONT1>120</NUTR_CONT1><NUTR_CONT2>20</NUTR_CONT2><NUTR_CONT3>12</NUTR_CONT3><NUTR_CONT4>0</NUTR_CONT4><NUTR_CONT5>18</NUTR_CONT5><NUTR_CONT6>200</NUTR_CONT6><NUTR_CONT7>0</NUTR_CONT7><NUTR_CONT8>0</NUTR_CONT8><NUTR_CONT9>0</NUTR_CONT9><BGN_YEAR>2017</BGN_YEAR><ANIMAL_PLANT>매일유업</ANIMAL_PLANT></item><item><DESC_KOR>앱솔루트W베이비</DESC_KOR><SERVING_WT>100</SERVING_WT><NUTR_CONT1>65</NUTR_CONT1><NUTR_CONT2>4.5</NUTR_CONT2><NUTR_CONT3>3</NUTR_CONT3><NUTR_CONT4>4</NUTR_CONT4><NUTR_CONT5>4.5</NUTR_CONT5><NUTR_CONT6>50</NUTR_CONT6><NUTR_CONT7>15</NUTR_CONT7><NUTR_CONT8>2.5</NUTR_CONT8><NUTR_CONT9>0</NUTR_CONT9><BGN_YEAR>2015</BGN_YEAR><ANIMAL_PLANT>매일유업</ANIMAL_PLANT></item><item><DESC_KOR>앱솔루트W베이비</DESC_KOR><SERVING_WT>100</SERVING_WT><NUTR_CONT1>65</NUTR_CONT1><NUTR_CONT2>4.5</NUTR_CONT2><NUTR_CONT3>3</NUTR_CONT3><NUTR_CONT4>4</NUTR_CONT4><NUTR_CONT5>4.5</NUTR_CONT5><NUTR_CONT6>50</NUTR_CONT6><NUTR_CONT7>15</NUTR_CONT7><NUTR_CONT8>2.5</NUTR_CONT8><NUTR_CONT9>0</NUTR_CONT9><BGN_YEAR>2017</BGN_YEAR><ANIMAL_PLANT>매일유업</ANIMAL_PLANT></item><item><DESC_KOR>앱솔루트W어린이</DESC_KOR><SERVING_WT>100</SERVING_WT><NUTR_CONT1>65</NUTR_CONT1><NUTR_CONT2>4.5</NUTR_CONT2><NUTR_CONT3>3</NUTR_CONT3><NUTR_CONT4>4</NUTR_CONT4><NUTR_CONT5>4.5</NUTR_CONT5><NUTR_CONT6>50</NUTR_CONT6><NUTR_CONT7>15</NUTR_CONT7><NUTR_CONT8>2.5</NUTR_CONT8><NUTR_CONT9>0</NUTR_CONT9><BGN_YEAR>2015</BGN_YEAR><ANIMAL_PLANT>매일유업</ANIMAL_PLANT></item><item><DESC_KOR>앱솔루트W어린이</DESC_KOR><SERVING_WT>100</SERVING_WT><NUTR_CONT1>65</NUTR_CONT1><NUTR_CONT2>4.5</NUTR_CONT2><NUTR_CONT3>3</NUTR_CONT3><NUTR_CONT4>4</NUTR_CONT4><NUTR_CONT5>4.5</NUTR_CONT5><NUTR_CONT6>50</NUTR_CONT6><NUTR_CONT7>15</NUTR_CONT7><NUTR_CONT8>2.5</NUTR_CONT8><NUTR_CONT9>0</NUTR_CONT9><BGN_YEAR>2017</BGN_YEAR><ANIMAL_PLANT>매일유업</ANIMAL_PLANT></item><item><DESC_KOR>새벽목장오메가3&amp;칼슘</DESC_KOR><SERVING_WT>200</SERVING_WT><NUTR_CONT1>130</NUTR_CONT1><NUTR_CONT2>9.4</NUTR_CONT2><NUTR_CONT3>6</NUTR_CONT3><NUTR_CONT4>8</NUTR_CONT4><NUTR_CONT5>9.4</NUTR_CONT5><NUTR_CONT6>100</NUTR_CONT6><NUTR_CONT7>30</NUTR_CONT7><NUTR_CONT8>5</NUTR_CONT8><NUTR_CONT9>0</NUTR_CONT9><BGN_YEAR>2015</BGN_YEAR><ANIMAL_PLANT>매일유업</ANIMAL_PLANT></item><item><DESC_KOR>새벽목장오메가3&amp;칼슘</DESC_KOR><SERVING_WT>200</SERVING_WT><NUTR_CONT1>260</NUTR_CONT1><NUTR_CONT2>18.8</NUTR_CONT2><NUTR_CONT3>12</NUTR_CONT3><NUTR_CONT4>16</NUTR_CONT4><NUTR_CONT5>18.61</NUTR_CONT5><NUTR_CONT6>200</NUTR_CONT6><NUTR_CONT7>60</NUTR_CONT7><NUTR_CONT8>10</NUTR_CONT8><NUTR_CONT9>0</NUTR_CONT9><BGN_YEAR>2017</BGN_YEAR><ANIMAL_PLANT>매일유업</ANIMAL_PLANT></item><item><DESC_KOR>새벽목장저지방&amp;고칼슘</DESC_KOR><SERVING_WT>200</SERVING_WT><NUTR_CONT1>80</NUTR_CONT1><NUTR_CONT2>10</NUTR_CONT2><NUTR_CONT3>6</NUTR_CONT3><NUTR_CONT4>2</NUTR_CONT4><NUTR_CONT5>9</NUTR_CONT5><NUTR_CONT6>100</NUTR_CONT6><NUTR_CONT7>7.4</NUTR_CONT7><NUTR_CONT8>1.2</NUTR_CONT8><NUTR_CONT9>0</NUTR_CONT9><BGN_YEAR>2015</BGN_YEAR><ANIMAL_PLANT>매일유업</ANIMAL_PLANT></item><item><DESC_KOR>새벽목장저지방&amp;고칼슘</DESC_KOR><SERVING_WT>200</SERVING_WT><NUTR_CONT1>160</NUTR_CONT1><NUTR_CONT2>20</NUTR_CONT2><NUTR_CONT3>12</NUTR_CONT3><NUTR_CONT4>4</NUTR_CONT4><NUTR_CONT5>18</NUTR_CONT5><NUTR_CONT6>200</NUTR_CONT6><NUTR_CONT7>14.8</NUTR_CONT7><NUTR_CONT8>2.4</NUTR_CONT8><NUTR_CONT9>0</NUTR_CONT9><BGN_YEAR>2017</BGN_YEAR><ANIMAL_PLANT>매일유업</ANIMAL_PLANT></item><item><DESC_KOR>(CU)CU(씨유)우유저지방</DESC_KOR><SERVING_WT>200</SERVING_WT><NUTR_CONT1>80</NUTR_CONT1><NUTR_CONT2>10</NUTR_CONT2><NUTR_CONT3>6</NUTR_CONT3><NUTR_CONT4>2</NUTR_CONT4><NUTR_CONT5>9</NUTR_CONT5><NUTR_CONT6>100</NUTR_CONT6><NUTR_CONT7>7.4</NUTR_CONT7><NUTR_CONT8>1.2</NUTR_CONT8><NUTR_CONT9>0</NUTR_CONT9><BGN_YEAR>2015</BGN_YEAR><ANIMAL_PLANT>매일유업</ANIMAL_PLANT></item><item><DESC_KOR>(CU)CU(씨유)우유저지방</DESC_KOR><SERVING_WT>200</SERVING_WT><NUTR_CONT1>160</NUTR_CONT1><NUTR_CONT2>20</NUTR_CONT2><NUTR_CONT3>12</NUTR_CONT3><NUTR_CONT4>4</NUTR_CONT4><NUTR_CONT5>18.44</NUTR_CONT5><NUTR_CONT6>200</NUTR_CONT6><NUTR_CONT7>14.8</NUTR_CONT7><NUTR_CONT8>2.4</NUTR_CONT8><NUTR_CONT9>0</NUTR_CONT9><BGN_YEAR>2017</BGN_YEAR><ANIMAL_PLANT>매일유업</ANIMAL_PLANT></item><item><DESC_KOR>매일바이오플레인요거트</DESC_KOR><SERVING_WT>100</SERVING_WT><NUTR_CONT1>77.77</NUTR_CONT1><NUTR_CONT2>5.56</NUTR_CONT2><NUTR_CONT3>4.44</NUTR_CONT3><NUTR_CONT4>4.11</NUTR_CONT4><NUTR_CONT5>5.56</NUTR_CONT5><NUTR_CONT6>72.22</NUTR_CONT6><NUTR_CONT7>11.11</NUTR_CONT7><NUTR_CONT8>2.67</NUTR_CONT8><NUTR_CONT9>0</NUTR_CONT9><BGN_YEAR>2015</BGN_YEAR><ANIMAL_PLANT>매일유업</ANIMAL_PLANT></item><item><DESC_KOR>매일바이오플레인요거트</DESC_KOR><SERVING_WT>100</SERVING_WT><NUTR_CONT1>77.77</NUTR_CONT1><NUTR_CONT2>5.56</NUTR_CONT2><NUTR_CONT3>4.44</NUTR_CONT3><NUTR_CONT4>4.11</NUTR_CONT4><NUTR_CONT5>8.75</NUTR_CONT5><NUTR_CONT6>72.22</NUTR_CONT6><NUTR_CONT7>11.11</NUTR_CONT7><NUTR_CONT8>2.67</NUTR_CONT8><NUTR_CONT9>0</NUTR_CONT9><BGN_YEAR>2017</BGN_YEAR><ANIMAL_PLANT>매일유업</ANIMAL_PLANT></item><item><DESC_KOR>매일바이오플레인저지방</DESC_KOR><SERVING_WT>100</SERVING_WT><NUTR_CONT1>61.11</NUTR_CONT1><NUTR_CONT2>6.67</NUTR_CONT2><NUTR_CONT3>5</NUTR_CONT3><NUTR_CONT4>1.44</NUTR_CONT4><NUTR_CONT5>5.56</NUTR_CONT5><NUTR_CONT6>66.67</NUTR_CONT6><NUTR_CONT7>5.56</NUTR_CONT7><NUTR_CONT8>0.78</NUTR_CONT8><NUTR_CONT9>0</NUTR_CONT9><BGN_YEAR>2015</BGN_YEAR><ANIMAL_PLANT>매일유업</ANIMAL_PLANT></item><item><DESC_KOR>매일바이오플레인저지방</DESC_KOR><SERVING_WT>100</SERVING_WT><NUTR_CONT1>61.11</NUTR_CONT1><NUTR_CONT2>6.67</NUTR_CONT2><NUTR_CONT3>5</NUTR_CONT3><NUTR_CONT4>1.44</NUTR_CONT4><NUTR_CONT5>5.56</NUTR_CONT5><NUTR_CONT6>66.67</NUTR_CONT6><NUTR_CONT7>5.56</NUTR_CONT7><NUTR_CONT8>0.78</NUTR_CONT8><NUTR_CONT9>0</NUTR_CONT9><BGN_YEAR>2017</BGN_YEAR><ANIMAL_PLANT>매일유업</ANIMAL_PLANT></item><item><DESC_KOR>매일바이오딸기</DESC_KOR><SERVING_WT>100</SERVING_WT><NUTR_CONT1>94.4</NUTR_CONT1><NUTR_CONT2>15.55</NUTR_CONT2><NUTR_CONT3>3.55</NUTR_CONT3><NUTR_CONT4>1.88</NUTR_CONT4><NUTR_CONT5>15</NUTR_CONT5><NUTR_CONT6>66.67</NUTR_CONT6><NUTR_CONT7>5.56</NUTR_CONT7><NUTR_CONT8>1.11</NUTR_CONT8><NUTR_CONT9>0</NUTR_CONT9><BGN_YEAR>2015</BGN_YEAR><ANIMAL_PLANT>매일유업</ANIMAL_PLANT></item><item><DESC_KOR>매일바이오딸기</DESC_KOR><SERVING_WT>100</SERVING_WT><NUTR_CONT1>94.4</NUTR_CONT1><NUTR_CONT2>15.55</NUTR_CONT2><NUTR_CONT3>3.55</NUTR_CONT3><NUTR_CONT4>1.88</NUTR_CONT4><NUTR_CONT5>8.75</NUTR_CONT5><NUTR_CONT6>66.67</NUTR_CONT6><NUTR_CONT7>5.56</NUTR_CONT7><NUTR_CONT8>1.11</NUTR_CONT8><NUTR_CONT9>0</NUTR_CONT9><BGN_YEAR>2017</BGN_YEAR><ANIMAL_PLANT>매일유업</ANIMAL_PLANT></item><item><DESC_KOR>매일바이오복숭아</DESC_KOR><SERVING_WT>100</SERVING_WT><NUTR_CONT1>94.44</NUTR_CONT1><NUTR_CONT2>15.55</NUTR_CONT2><NUTR_CONT3>3.55</NUTR_CONT3><NUTR_CONT4>1.89</NUTR_CONT4><NUTR_CONT5>15</NUTR_CONT5><NUTR_CONT6>66.67</NUTR_CONT6><NUTR_CONT7>5.56</NUTR_CONT7><NUTR_CONT8>1.11</NUTR_CONT8><NUTR_CONT9>0</NUTR_CONT9><BGN_YEAR>2015</BGN_YEAR><ANIMAL_PLANT>매일유업</ANIMAL_PLANT></item><item><DESC_KOR>매일바이오복숭아</DESC_KOR><SERVING_WT>100</SERVING_WT><NUTR_CONT1>94.44</NUTR_CONT1><NUTR_CONT2>15.55</NUTR_CONT2><NUTR_CONT3>3.55</NUTR_CONT3><NUTR_CONT4>1.89</NUTR_CONT4><NUTR_CONT5>8.75</NUTR_CONT5><NUTR_CONT6>66.67</NUTR_CONT6><NUTR_CONT7>5.56</NUTR_CONT7><NUTR_CONT8>1.11</NUTR_CONT8><NUTR_CONT9>0</NUTR_CONT9><BGN_YEAR>2017</BGN_YEAR><ANIMAL_PLANT>매일유업</ANIMAL_PLANT></item><item><DESC_KOR>매일바이오코코포도</DESC_KOR><SERVING_WT>150</SERVING_WT><NUTR_CONT1>141.67</NUTR_CONT1><NUTR_CONT2>23.33</NUTR_CONT2><NUTR_CONT3>5.33</NUTR_CONT3><NUTR_CONT4>2.83</NUTR_CONT4><NUTR_CONT5>22.5</NUTR_CONT5><NUTR_CONT6>100</NUTR_CONT6><NUTR_CONT7>8.33</NUTR_CONT7><NUTR_CONT8>1.67</NUTR_CONT8><NUTR_CONT9>0</NUTR_CONT9><BGN_YEAR>2015</BGN_YEAR><ANIMAL_PLANT>매일유업</ANIMAL_PLANT></item><item><DESC_KOR>매일바이오코코포도</DESC_KOR><SERVING_WT>150</SERVING_WT><NUTR_CONT1>212.5</NUTR_CONT1><NUTR_CONT2>35</NUTR_CONT2><NUTR_CONT3>8</NUTR_CONT3><NUTR_CONT4>4.25</NUTR_CONT4><NUTR_CONT5>29.07</NUTR_CONT5><NUTR_CONT6>150</NUTR_CONT6><NUTR_CONT7>12.5</NUTR_CONT7><NUTR_CONT8>2.5</NUTR_CONT8><NUTR_CONT9>0</NUTR_CONT9><BGN_YEAR>2017</BGN_YEAR><ANIMAL_PLANT>매일유업</ANIMAL_PLANT></item><item><DESC_KOR>매일바이오블루베리</DESC_KOR><SERVING_WT>100</SERVING_WT><NUTR_CONT1>94.44</NUTR_CONT1><NUTR_CONT2>15.56</NUTR_CONT2><NUTR_CONT3>3.56</NUTR_CONT3><NUTR_CONT4>1.89</NUTR_CONT4><NUTR_CONT5>15</NUTR_CONT5><NUTR_CONT6>66.67</NUTR_CONT6><NUTR_CONT7>5.56</NUTR_CONT7><NUTR_CONT8>1.11</NUTR_CONT8><NUTR_CONT9>0</NUTR_CONT9><BGN_YEAR>2015</BGN_YEAR><ANIMAL_PLANT>매일유업</ANIMAL_PLANT></item><item><DESC_KOR>매일바이오블루베리</DESC_KOR><SERVING_WT>100</SERVING_WT><NUTR_CONT1>94.44</NUTR_CONT1><NUTR_CONT2>15.56</NUTR_CONT2><NUTR_CONT3>3.56</NUTR_CONT3><NUTR_CONT4>1.89</NUTR_CONT4><NUTR_CONT5>6</NUTR_CONT5><NUTR_CONT6>66.67</NUTR_CONT6><NUTR_CONT7>5.56</NUTR_CONT7><NUTR_CONT8>1.11</NUTR_CONT8><NUTR_CONT9>0</NUTR_CONT9><BGN_YEAR>2017</BGN_YEAR><ANIMAL_PLANT>매일유업</ANIMAL_PLANT></item><item><DESC_KOR>매일바이오플레인로슈거</DESC_KOR><SERVING_WT>100</SERVING_WT><NUTR_CONT1>72.22</NUTR_CONT1><NUTR_CONT2>10.56</NUTR_CONT2><NUTR_CONT3>3.67</NUTR_CONT3><NUTR_CONT4>1.44</NUTR_CONT4><NUTR_CONT5>9.78</NUTR_CONT5><NUTR_CONT6>66.67</NUTR_CONT6><NUTR_CONT7>5.56</NUTR_CONT7><NUTR_CONT8>0.78</NUTR_CONT8><NUTR_CONT9>0</NUTR_CONT9><BGN_YEAR>2015</BGN_YEAR><ANIMAL_PLANT>매일유업</ANIMAL_PLANT></item><item><DESC_KOR>매일바이오플레인로슈거</DESC_KOR><SERVING_WT>100</SERVING_WT><NUTR_CONT1>72.22</NUTR_CONT1><NUTR_CONT2>10.56</NUTR_CONT2><NUTR_CONT3>3.67</NUTR_CONT3><NUTR_CONT4>1.44</NUTR_CONT4><NUTR_CONT5>12.5</NUTR_CONT5><NUTR_CONT6>66.67</NUTR_CONT6><NUTR_CONT7>5.56</NUTR_CONT7><NUTR_CONT8>0.78</NUTR_CONT8><NUTR_CONT9>0</NUTR_CONT9><BGN_YEAR>2017</BGN_YEAR><ANIMAL_PLANT>매일유업</ANIMAL_PLANT></item><item><DESC_KOR>진심을담은플레인요거트</DESC_KOR><SERVING_WT>100</SERVING_WT><NUTR_CONT1>77.77</NUTR_CONT1><NUTR_CONT2>5.56</NUTR_CONT2><NUTR_CONT3>4.44</NUTR_CONT3><NUTR_CONT4>4.11</NUTR_CONT4><NUTR_CONT5>5.56</NUTR_CONT5><NUTR_CONT6>72.22</NUTR_CONT6><NUTR_CONT7>11.11</NUTR_CONT7><NUTR_CONT8>2.67</NUTR_CONT8><NUTR_CONT9>0</NUTR_CONT9><BGN_YEAR>2015</BGN_YEAR><ANIMAL_PLANT>매일유업</ANIMAL_PLANT></item><item><DESC_KOR>진심을담은플레인요거트</DESC_KOR><SERVING_WT>100</SERVING_WT><NUTR_CONT1>77.77</NUTR_CONT1><NUTR_CONT2>5.56</NUTR_CONT2><NUTR_CONT3>4.44</NUTR_CONT3><NUTR_CONT4>4.11</NUTR_CONT4><NUTR_CONT5>13.33</NUTR_CONT5><NUTR_CONT6>72.22</NUTR_CONT6><NUTR_CONT7>11.11</NUTR_CONT7><NUTR_CONT8>2.67</NUTR_CONT8><NUTR_CONT9>0</NUTR_CONT9><BGN_YEAR>2017</BGN_YEAR><ANIMAL_PLANT>매일유업</ANIMAL_PLANT></item></items></body></response>